deepdiff_viewer/__init__.py
deepdiff_viewer/base.py
deepdiff_viewer/rich.py
deepdiff_viewer-0.1.1.dist-info/LICENSE
deepdiff_viewer-0.1.1.dist-info/METADATA
deepdiff_viewer-0.1.1.dist-info/WHEEL
deepdiff_viewer-0.1.1.dist-info/RECORD
