Metadata-Version: 2.1
Name: deepdiff-viewer
Version: 0.1.1
Summary: Viewer tools for the `DeepDiff` object of the `deepdiff` library.
License: MIT
Author: Baptiste Bourdet
Author-email: bat.bourdet@gmail.com
Requires-Python: >=3.10,<4.0
Classifier: License :: OSI Approved :: MIT License
Classifier: Programming Language :: Python :: 3
Classifier: Programming Language :: Python :: 3.10
Classifier: Programming Language :: Python :: 3.11
Provides-Extra: rich
Requires-Dist: deepdiff (>=6.3.1,<7.0.0)
Requires-Dist: pyyaml (>=6.0.1,<7.0.0) ; extra == "rich"
Requires-Dist: rich (>=13.4.2,<14.0.0) ; extra == "rich"
